webcrawl_pack.py
crawl_web_page_script-2.0.3.dist-info/METADATA
crawl_web_page_script-2.0.3.dist-info/WHEEL
crawl_web_page_script-2.0.3.dist-info/top_level.txt
crawl_web_page_script-2.0.3.dist-info/RECORD
