Metadata-Version: 2.1
Name: crawl-web-page-script
Version: 2.0.3
Summary: UNKNOWN
Home-page: UNKNOWN
License: UNKNOWN
Platform: UNKNOWN
Requires-Python: >=3.6, <4
Requires-Dist: requests
